trytond/modules/account_es/__init__.py
trytond/modules/account_es/account.py
trytond/modules/account_es/account_normal.xml
trytond/modules/account_es/account_payment.py
trytond/modules/account_es/account_payment.xml
trytond/modules/account_es/account_pyme.xml
trytond/modules/account_es/aeat111.txt
trytond/modules/account_es/aeat115.txt
trytond/modules/account_es/aeat303.txt
trytond/modules/account_es/aeat347.txt
trytond/modules/account_es/aeat349.txt
trytond/modules/account_es/company.py
trytond/modules/account_es/exceptions.py
trytond/modules/account_es/message.xml
trytond/modules/account_es/party.py
trytond/modules/account_es/party.xml
trytond/modules/account_es/reporting_tax.py
trytond/modules/account_es/reporting_tax.xml
trytond/modules/account_es/tax_groups.xml
trytond/modules/account_es/tax_normal.xml
trytond/modules/account_es/tax_pyme.xml
trytond/modules/account_es/tryton.cfg
trytond/modules/account_es/view.xml
trytond/modules/account_es/locale/bg.po
trytond/modules/account_es/locale/ca.po
trytond/modules/account_es/locale/cs.po
trytond/modules/account_es/locale/de.po
trytond/modules/account_es/locale/es.po
trytond/modules/account_es/locale/es_419.po
trytond/modules/account_es/locale/et.po
trytond/modules/account_es/locale/fa.po
trytond/modules/account_es/locale/fi.po
trytond/modules/account_es/locale/fr.po
trytond/modules/account_es/locale/hu.po
trytond/modules/account_es/locale/id.po
trytond/modules/account_es/locale/it.po
trytond/modules/account_es/locale/lo.po
trytond/modules/account_es/locale/lt.po
trytond/modules/account_es/locale/nl.po
trytond/modules/account_es/locale/pl.po
trytond/modules/account_es/locale/pt.po
trytond/modules/account_es/locale/ro.po
trytond/modules/account_es/locale/ru.po
trytond/modules/account_es/locale/sl.po
trytond/modules/account_es/locale/tr.po
trytond/modules/account_es/locale/uk.po
trytond/modules/account_es/locale/zh_CN.po
trytond/modules/account_es/tests/111.txt
trytond/modules/account_es/tests/115.txt
trytond_account_es-7.8.0.dist-info/licenses/LICENSE
trytond_account_es-7.8.0.dist-info/METADATA
trytond_account_es-7.8.0.dist-info/WHEEL
trytond_account_es-7.8.0.dist-info/entry_points.txt
trytond_account_es-7.8.0.dist-info/top_level.txt
trytond_account_es-7.8.0.dist-info/RECORD
