Metadata-Version: 2.4
Name: trytond_account_es
Version: 7.8.0
Summary: Tryton with Spanish chart of accounts
Home-page: http://www.tryton.org/
Download-URL: http://downloads.tryton.org/7.8/
Author: Tryton
Author-email: foundation@tryton.org
License: GPL-3
Project-URL: Bug Tracker, https://bugs.tryton.org/
Project-URL: Documentation, https://docs.tryton.org/latest/modules-account-es/
Project-URL: Forum, https://www.tryton.org/forum
Project-URL: Source Code, https://code.tryton.org/tryton
Keywords: tryton account chart spanish
Classifier: Development Status :: 5 - Production/Stable
Classifier: Environment :: Plugins
Classifier: Framework :: Tryton
Classifier: Intended Audience :: Developers
Classifier: Intended Audience :: Financial and Insurance Industry
Classifier: Intended Audience :: Legal Industry
Classifier: License :: OSI Approved :: GNU General Public License v3 or later (GPLv3+)
Classifier: Natural Language :: Spanish
Classifier: Operating System :: OS Independent
Classifier: Programming Language :: Python :: 3
Classifier: Programming Language :: Python :: 3.9
Classifier: Programming Language :: Python :: 3.10
Classifier: Programming Language :: Python :: 3.11
Classifier: Programming Language :: Python :: 3.12
Classifier: Programming Language :: Python :: 3.13
Classifier: Programming Language :: Python :: Implementation :: CPython
Classifier: Topic :: Office/Business
Classifier: Topic :: Office/Business :: Financial :: Accounting
Requires-Python: >=3.9
License-File: LICENSE
Requires-Dist: python-sql>=1.1.0
Requires-Dist: trytond_company<7.9,>=7.8
Requires-Dist: trytond_currency<7.9,>=7.8
Requires-Dist: trytond_account<7.9,>=7.8
Requires-Dist: trytond_account_eu<7.9,>=7.8
Requires-Dist: trytond_account_invoice<7.9,>=7.8
Requires-Dist: trytond_party<7.9,>=7.8
Requires-Dist: trytond<7.9,>=7.8
Provides-Extra: test
Requires-Dist: proteus<7.9,>=7.8; extra == "test"
Requires-Dist: trytond_account_asset<7.9,>=7.8; extra == "test"
Requires-Dist: trytond_account_payment_sepa<7.9,>=7.8; extra == "test"
Requires-Dist: trytond_sale_advance_payment<7.9,>=7.8; extra == "test"
Requires-Dist: trytond_sale_gift_card<7.9,>=7.8; extra == "test"
Dynamic: author
Dynamic: author-email
Dynamic: classifier
Dynamic: description
Dynamic: download-url
Dynamic: home-page
Dynamic: keywords
Dynamic: license
Dynamic: license-file
Dynamic: project-url
Dynamic: provides-extra
Dynamic: requires-dist
Dynamic: requires-python
Dynamic: summary
